casus/__init__.py
casus/encoders.py
casus/hypervectors/__init__.py
casus/hypervectors/base.py
casus/hypervectors/fourier.py
casus/hypervectors/map.py
casus/ml.py
casus/ops.py
casus-0.0.1.dist-info/LICENSE
casus-0.0.1.dist-info/METADATA
casus-0.0.1.dist-info/WHEEL
casus-0.0.1.dist-info/entry_points.txt
casus-0.0.1.dist-info/RECORD
